pylogstash.py
pylogstash_context-0.1.19.dist-info/COPYING
pylogstash_context-0.1.19.dist-info/METADATA
pylogstash_context-0.1.19.dist-info/WHEEL
pylogstash_context-0.1.19.dist-info/entry_points.txt
pylogstash_context-0.1.19.dist-info/top_level.txt
pylogstash_context-0.1.19.dist-info/RECORD
